{"510300.SH": [{"ts_code": "510300.SH", "trade_time": "2024-08-13 15:00:00", "close": 3.394, "open": 3.39, "high": 3.398, "low": 3.388, "vol": 121248300.0, "amount": 411485000.0}, {"ts_code": "510300.SH", "trade_time": "2024-08-13 14:45:00", "close": 3.391, "open": 3.379, "high": 3.391, "low": 3.379, "vol": 66366900.0, "amount": 224662560.0}, {"ts_code": "510300.SH", "trade_time": "2024-08-13 14:30:00", "close": 3.379, "open": 3.374, "high": 3.38, "low": 3.372, "vol": 35221700.0, "amount": 118901400.0}, {"ts_code": "510300.SH", "trade_time": "2024-08-13 14:15:00", "close": 3.375, "open": 3.382, "high": 3.383, "low": 3.373, "vol": 57860900.0, "amount": 195403980.0}, {"ts_code": "510300.SH", "trade_time": "2024-08-13 14:00:00", "close": 3.382, "open": 3.384, "high": 3.384, "low": 3.381, "vol": 14376700.0, "amount": 48620260.0}, {"ts_code": "510300.SH", "trade_time": "2024-08-13 13:45:00", "close": 3.383, "open": 3.385, "high": 3.386, "low": 3.382, "vol": 12960800.0, "amount": 43858416.0}, {"ts_code": "510300.SH", "trade_time": "2024-08-13 13:30:00", "close": 3.385, "open": 3.384, "high": 3.387, "low": 3.383, "vol": 15684100.0, "amount": 53100236.0}, {"ts_code": "510300.SH", "trade_time": "2024-08-13 13:15:00", "close": 3.384, "open": 3.382, "high": 3.386, "low": 3.381, "vol": 16213800.0, "amount": 54855570.0}, {"ts_code": "510300.SH", "trade_time": "2024-08-13 11:30:00", "close": 3.381, "open": 3.384, "high": 3.385, "low": 3.381, "vol": 22081200.0, "amount": 74701016.0}, {"ts_code": "510300.SH", "trade_time": "2024-08-13 11:15:00", "close": 3.383, "open": 3.387, "high": 3.389, "low": 3.383, "vol": 11979200.0, "amount": 40552190.0}, {"ts_code": "510300.SH", "trade_time": "2024-08-13 11:00:00", "close": 3.387, "open": 3.381, "high": 3.387, "low": 3.38, "vol": 28121800.0, "amount": 95187170.0}, {"ts_code": "510300.SH", "trade_time": "2024-08-13 10:45:00", "close": 3.381, "open": 3.382, "high": 3.383, "low": 3.378, "vol": 59140200.0, "amount": 199878980.0}, {"ts_code": "510300.SH", "trade_time": "2024-08-13 10:30:00", "close": 3.383, "open": 3.383, "high": 3.385, "low": 3.381, "vol": 33368800.0, "amount": 112881464.0}, {"ts_code": "510300.SH", "trade_time": "2024-08-13 10:15:00", "close": 3.384, "open": 3.384, "high": 3.394, "low": 3.377, "vol": 98644600.0, "amount": 333925630.0}, {"ts_code": "510300.SH", "trade_time": "2024-08-13 10:00:00", "close": 3.384, "open": 3.388, "high": 3.391, "low": 3.383, "vol": 26928400.0, "amount": 91185470.0}, {"ts_code": "510300.SH", "trade_time": "2024-08-13 09:45:00", "close": 3.388, "open": 3.392, "high": 3.395, "low": 3.383, "vol": 73589600.0, "amount": 249446720.0}, {"ts_code": "510300.SH", "trade_time": "2024-08-13 09:30:00", "close": 3.391, "open": 3.391, "high": 3.391, "low": 3.391, "vol": 2019300.0, "amount": 6847446.0}], "159919.SZ": [{"ts_code": "159919.SZ", "trade_time": "2024-08-13 15:00:00", "close": 3.526, "open": 3.522, "high": 3.529, "low": 3.52, "vol": 17828800.0, "amount": 62855384.0}, {"ts_code": "159919.SZ", "trade_time": "2024-08-13 14:45:00", "close": 3.523, "open": 3.51, "high": 3.523, "low": 3.51, "vol": 13571900.0, "amount": 47711484.0}, {"ts_code": "159919.SZ", "trade_time": "2024-08-13 14:30:00", "close": 3.511, "open": 3.506, "high": 3.512, "low": 3.504, "vol": 11068700.0, "amount": 38826810.0}, {"ts_code": "159919.SZ", "trade_time": "2024-08-13 14:15:00", "close": 3.507, "open": 3.514, "high": 3.515, "low": 3.504, "vol": 15922649.0, "amount": 55892068.0}, {"ts_code": "159919.SZ", "trade_time": "2024-08-13 14:00:00", "close": 3.514, "open": 3.516, "high": 3.516, "low": 3.513, "vol": 8166700.0, "amount": 28697124.0}, {"ts_code": "159919.SZ", "trade_time": "2024-08-13 13:45:00", "close": 3.515, "open": 3.518, "high": 3.518, "low": 3.514, "vol": 4351600.0, "amount": 15301722.0}, {"ts_code": "159919.SZ", "trade_time": "2024-08-13 13:30:00", "close": 3.517, "open": 3.517, "high": 3.521, "low": 3.517, "vol": 2321500.0, "amount": 8168031.0}, {"ts_code": "159919.SZ", "trade_time": "2024-08-13 13:15:00", "close": 3.517, "open": 3.514, "high": 3.518, "low": 3.514, "vol": 3514500.0, "amount": 12357236.0}, {"ts_code": "159919.SZ", "trade_time": "2024-08-13 11:30:00", "close": 3.515, "open": 3.516, "high": 3.518, "low": 3.515, "vol": 2312900.0, "amount": 8131794.5}, {"ts_code": "159919.SZ", "trade_time": "2024-08-13 11:15:00", "close": 3.517, "open": 3.52, "high": 3.522, "low": 3.516, "vol": 4545800.0, "amount": 16002881.0}, {"ts_code": "159919.SZ", "trade_time": "2024-08-13 11:00:00", "close": 3.521, "open": 3.513, "high": 3.521, "low": 3.513, "vol": 15685800.0, "amount": 55169590.0}, {"ts_code": "159919.SZ", "trade_time": "2024-08-13 10:45:00", "close": 3.512, "open": 3.516, "high": 3.516, "low": 3.51, "vol": 4437451.0, "amount": 15583016.0}, {"ts_code": "159919.SZ", "trade_time": "2024-08-13 10:30:00", "close": 3.516, "open": 3.515, "high": 3.517, "low": 3.513, "vol": 8194300.0, "amount": 28803992.0}, {"ts_code": "159919.SZ", "trade_time": "2024-08-13 10:15:00", "close": 3.516, "open": 3.516, "high": 3.526, "low": 3.51, "vol": 19353600.0, "amount": 68078830.0}, {"ts_code": "159919.SZ", "trade_time": "2024-08-13 10:00:00", "close": 3.516, "open": 3.521, "high": 3.524, "low": 3.516, "vol": 8146800.0, "amount": 28676208.0}, {"ts_code": "159919.SZ", "trade_time": "2024-08-13 09:45:00", "close": 3.521, "open": 3.528, "high": 3.528, "low": 3.516, "vol": 9794000.0, "amount": 34491184.0}, {"ts_code": "159919.SZ", "trade_time": "2024-08-13 09:30:00", "close": 3.525, "open": 3.525, "high": 3.526, "low": 3.525, "vol": 362800.0, "amount": 1278891.1}], "510050.SH": [{"ts_code": "510050.SH", "trade_time": "2024-08-13 15:00:00", "close": 2.403, "open": 2.403, "high": 2.406, "low": 2.4, "vol": 71951720.0, "amount": 172880580.0}, {"ts_code": "510050.SH", "trade_time": "2024-08-13 14:45:00", "close": 2.403, "open": 2.394, "high": 2.403, "low": 2.393, "vol": 53650900.0, "amount": 128665830.0}, {"ts_code": "510050.SH", "trade_time": "2024-08-13 14:30:00", "close": 2.394, "open": 2.392, "high": 2.395, "low": 2.39, "vol": 21272100.0, "amount": 50898164.0}, {"ts_code": "510050.SH", "trade_time": "2024-08-13 14:15:00", "close": 2.392, "open": 2.396, "high": 2.397, "low": 2.39, "vol": 33127600.0, "amount": 79291200.0}, {"ts_code": "510050.SH", "trade_time": "2024-08-13 14:00:00", "close": 2.396, "open": 2.396, "high": 2.397, "low": 2.395, "vol": 6472700.0, "amount": 15508328.0}, {"ts_code": "510050.SH", "trade_time": "2024-08-13 13:45:00", "close": 2.396, "open": 2.396, "high": 2.398, "low": 2.395, "vol": 8292900.0, "amount": 19875036.0}, {"ts_code": "510050.SH", "trade_time": "2024-08-13 13:30:00", "close": 2.396, "open": 2.395, "high": 2.397, "low": 2.395, "vol": 18696600.0, "amount": 44795696.0}, {"ts_code": "510050.SH", "trade_time": "2024-08-13 13:15:00", "close": 2.396, "open": 2.397, "high": 2.398, "low": 2.394, "vol": 14363200.0, "amount": 34416096.0}, {"ts_code": "510050.SH", "trade_time": "2024-08-13 11:30:00", "close": 2.397, "open": 2.396, "high": 2.397, "low": 2.395, "vol": 20084200.0, "amount": 48123532.0}, {"ts_code": "510050.SH", "trade_time": "2024-08-13 11:15:00", "close": 2.396, "open": 2.398, "high": 2.4, "low": 2.396, "vol": 15045700.0, "amount": 36080440.0}, {"ts_code": "510050.SH", "trade_time": "2024-08-13 11:00:00", "close": 2.397, "open": 2.395, "high": 2.399, "low": 2.394, "vol": 21594500.0, "amount": 51754996.0}, {"ts_code": "510050.SH", "trade_time": "2024-08-13 10:45:00", "close": 2.394, "open": 2.397, "high": 2.397, "low": 2.393, "vol": 21819500.0, "amount": 52248810.0}, {"ts_code": "510050.SH", "trade_time": "2024-08-13 10:30:00", "close": 2.396, "open": 2.396, "high": 2.398, "low": 2.395, "vol": 22556600.0, "amount": 54052300.0}, {"ts_code": "510050.SH", "trade_time": "2024-08-13 10:15:00", "close": 2.397, "open": 2.398, "high": 2.404, "low": 2.393, "vol": 40761400.0, "amount": 97750870.0}, {"ts_code": "510050.SH", "trade_time": "2024-08-13 10:00:00", "close": 2.399, "open": 2.402, "high": 2.403, "low": 2.398, "vol": 44798700.0, "amount": 107532056.0}, {"ts_code": "510050.SH", "trade_time": "2024-08-13 09:45:00", "close": 2.402, "open": 2.404, "high": 2.407, "low": 2.399, "vol": 68009500.0, "amount": 163492660.0}, {"ts_code": "510050.SH", "trade_time": "2024-08-13 09:30:00", "close": 2.404, "open": 2.403, "high": 2.404, "low": 2.403, "vol": 489301.0, "amount": 1175831.0}], "159915.SZ": [{"ts_code": "159915.SZ", "trade_time": "2024-08-13 15:00:00", "close": 1.578, "open": 1.572, "high": 1.578, "low": 1.57, "vol": 113587710.0, "amount": 178894800.0}, {"ts_code": "159915.SZ", "trade_time": "2024-08-13 14:45:00", "close": 1.572, "open": 1.564, "high": 1.572, "low": 1.564, "vol": 49597700.0, "amount": 77766670.0}, {"ts_code": "159915.SZ", "trade_time": "2024-08-13 14:30:00", "close": 1.564, "open": 1.561, "high": 1.564, "low": 1.56, "vol": 34963300.0, "amount": 54584484.0}, {"ts_code": "159915.SZ", "trade_time": "2024-08-13 14:15:00", "close": 1.561, "open": 1.565, "high": 1.566, "low": 1.56, "vol": 30633000.0, "amount": 47860532.0}, {"ts_code": "159915.SZ", "trade_time": "2024-08-13 14:00:00", "close": 1.565, "open": 1.565, "high": 1.566, "low": 1.564, "vol": 17694300.0, "amount": 27683834.0}, {"ts_code": "159915.SZ", "trade_time": "2024-08-13 13:45:00", "close": 1.565, "open": 1.567, "high": 1.568, "low": 1.565, "vol": 17799700.0, "amount": 27886112.0}, {"ts_code": "159915.SZ", "trade_time": "2024-08-13 13:30:00", "close": 1.567, "open": 1.566, "high": 1.573, "low": 1.566, "vol": 71571700.0, "amount": 112393400.0}, {"ts_code": "159915.SZ", "trade_time": "2024-08-13 13:15:00", "close": 1.567, "open": 1.562, "high": 1.569, "low": 1.561, "vol": 66861600.0, "amount": 104732460.0}, {"ts_code": "159915.SZ", "trade_time": "2024-08-13 11:30:00", "close": 1.562, "open": 1.563, "high": 1.564, "low": 1.56, "vol": 13173600.0, "amount": 20576904.0}, {"ts_code": "159915.SZ", "trade_time": "2024-08-13 11:15:00", "close": 1.564, "open": 1.564, "high": 1.565, "low": 1.561, "vol": 25007812.0, "amount": 39105020.0}, {"ts_code": "159915.SZ", "trade_time": "2024-08-13 11:00:00", "close": 1.564, "open": 1.56, "high": 1.564, "low": 1.559, "vol": 27470500.0, "amount": 42923960.0}, {"ts_code": "159915.SZ", "trade_time": "2024-08-13 10:45:00", "close": 1.56, "open": 1.562, "high": 1.562, "low": 1.558, "vol": 21744100.0, "amount": 33905064.0}, {"ts_code": "159915.SZ", "trade_time": "2024-08-13 10:30:00", "close": 1.562, "open": 1.56, "high": 1.563, "low": 1.559, "vol": 25314800.0, "amount": 39497476.0}, {"ts_code": "159915.SZ", "trade_time": "2024-08-13 10:15:00", "close": 1.561, "open": 1.56, "high": 1.568, "low": 1.558, "vol": 83327000.0, "amount": 130164584.0}, {"ts_code": "159915.SZ", "trade_time": "2024-08-13 10:00:00", "close": 1.561, "open": 1.564, "high": 1.568, "low": 1.559, "vol": 69010600.0, "amount": 107883624.0}, {"ts_code": "159915.SZ", "trade_time": "2024-08-13 09:45:00", "close": 1.564, "open": 1.563, "high": 1.565, "low": 1.558, "vol": 90971500.0, "amount": 141999170.0}, {"ts_code": "159915.SZ", "trade_time": "2024-08-13 09:30:00", "close": 1.563, "open": 1.562, "high": 1.563, "low": 1.561, "vol": 4876800.0, "amount": 7619003.0}], "588080.SH": [{"ts_code": "588080.SH", "trade_time": "2024-08-13 15:00:00", "close": 0.73, "open": 0.726, "high": 0.73, "low": 0.726, "vol": 47201220.0, "amount": 34392730.0}, {"ts_code": "588080.SH", "trade_time": "2024-08-13 14:45:00", "close": 0.727, "open": 0.722, "high": 0.727, "low": 0.722, "vol": 18343656.0, "amount": 13293438.0}, {"ts_code": "588080.SH", "trade_time": "2024-08-13 14:30:00", "close": 0.723, "open": 0.722, "high": 0.724, "low": 0.721, "vol": 29804054.0, "amount": 21526050.0}, {"ts_code": "588080.SH", "trade_time": "2024-08-13 14:15:00", "close": 0.722, "open": 0.724, "high": 0.725, "low": 0.722, "vol": 20231428.0, "amount": 14629382.0}, {"ts_code": "588080.SH", "trade_time": "2024-08-13 14:00:00", "close": 0.725, "open": 0.724, "high": 0.725, "low": 0.723, "vol": 15883931.0, "amount": 11500034.0}, {"ts_code": "588080.SH", "trade_time": "2024-08-13 13:45:00", "close": 0.724, "open": 0.724, "high": 0.725, "low": 0.724, "vol": 3228300.0, "amount": 2340217.0}, {"ts_code": "588080.SH", "trade_time": "2024-08-13 13:30:00", "close": 0.724, "open": 0.724, "high": 0.727, "low": 0.724, "vol": 20870348.0, "amount": 15145805.0}, {"ts_code": "588080.SH", "trade_time": "2024-08-13 13:15:00", "close": 0.725, "open": 0.724, "high": 0.726, "low": 0.723, "vol": 6838379.0, "amount": 4954240.0}, {"ts_code": "588080.SH", "trade_time": "2024-08-13 11:30:00", "close": 0.724, "open": 0.725, "high": 0.726, "low": 0.723, "vol": 5975034.0, "amount": 4327090.0}, {"ts_code": "588080.SH", "trade_time": "2024-08-13 11:15:00", "close": 0.725, "open": 0.725, "high": 0.726, "low": 0.724, "vol": 4051962.0, "amount": 2937687.0}, {"ts_code": "588080.SH", "trade_time": "2024-08-13 11:00:00", "close": 0.725, "open": 0.724, "high": 0.727, "low": 0.723, "vol": 14448880.0, "amount": 10482396.0}, {"ts_code": "588080.SH", "trade_time": "2024-08-13 10:45:00", "close": 0.723, "open": 0.724, "high": 0.724, "low": 0.723, "vol": 7135520.0, "amount": 5159918.0}, {"ts_code": "588080.SH", "trade_time": "2024-08-13 10:30:00", "close": 0.724, "open": 0.723, "high": 0.725, "low": 0.723, "vol": 17979100.0, "amount": 13004790.0}, {"ts_code": "588080.SH", "trade_time": "2024-08-13 10:15:00", "close": 0.724, "open": 0.725, "high": 0.727, "low": 0.723, "vol": 46369900.0, "amount": 33598760.0}, {"ts_code": "588080.SH", "trade_time": "2024-08-13 10:00:00", "close": 0.725, "open": 0.728, "high": 0.729, "low": 0.724, "vol": 55477200.0, "amount": 40286156.0}, {"ts_code": "588080.SH", "trade_time": "2024-08-13 09:45:00", "close": 0.728, "open": 0.726, "high": 0.728, "low": 0.725, "vol": 33682664.0, "amount": 24485420.0}, {"ts_code": "588080.SH", "trade_time": "2024-08-13 09:30:00", "close": 0.727, "open": 0.727, "high": 0.727, "low": 0.727, "vol": 344400.0, "amount": 250379.0}], "159949.SZ": [{"ts_code": "159949.SZ", "trade_time": "2024-08-13 15:00:00", "close": 0.69, "open": 0.687, "high": 0.691, "low": 0.686, "vol": 74114100.0, "amount": 51058696.0}, {"ts_code": "159949.SZ", "trade_time": "2024-08-13 14:45:00", "close": 0.688, "open": 0.684, "high": 0.688, "low": 0.683, "vol": 50178000.0, "amount": 34367536.0}, {"ts_code": "159949.SZ", "trade_time": "2024-08-13 14:30:00", "close": 0.684, "open": 0.682, "high": 0.684, "low": 0.681, "vol": 46550800.0, "amount": 31757534.0}, {"ts_code": "159949.SZ", "trade_time": "2024-08-13 14:15:00", "close": 0.682, "open": 0.684, "high": 0.685, "low": 0.682, "vol": 44709300.0, "amount": 30545894.0}, {"ts_code": "159949.SZ", "trade_time": "2024-08-13 14:00:00", "close": 0.684, "open": 0.684, "high": 0.685, "low": 0.683, "vol": 23890400.0, "amount": 16330367.0}, {"ts_code": "159949.SZ", "trade_time": "2024-08-13 13:45:00", "close": 0.685, "open": 0.685, "high": 0.686, "low": 0.684, "vol": 33917550.0, "amount": 23228184.0}, {"ts_code": "159949.SZ", "trade_time": "2024-08-13 13:30:00", "close": 0.685, "open": 0.685, "high": 0.689, "low": 0.685, "vol": 67045700.0, "amount": 46074256.0}, {"ts_code": "159949.SZ", "trade_time": "2024-08-13 13:15:00", "close": 0.685, "open": 0.682, "high": 0.687, "low": 0.681, "vol": 96585100.0, "amount": 66123120.0}, {"ts_code": "159949.SZ", "trade_time": "2024-08-13 11:30:00", "close": 0.681, "open": 0.683, "high": 0.683, "low": 0.681, "vol": 27678000.0, "amount": 18869104.0}, {"ts_code": "159949.SZ", "trade_time": "2024-08-13 11:15:00", "close": 0.684, "open": 0.683, "high": 0.684, "low": 0.682, "vol": 12067600.0, "amount": 8242621.5}, {"ts_code": "159949.SZ", "trade_time": "2024-08-13 11:00:00", "close": 0.683, "open": 0.681, "high": 0.683, "low": 0.681, "vol": 12167700.0, "amount": 8304719.0}, {"ts_code": "159949.SZ", "trade_time": "2024-08-13 10:45:00", "close": 0.682, "open": 0.682, "high": 0.682, "low": 0.68, "vol": 13972900.0, "amount": 9515646.0}, {"ts_code": "159949.SZ", "trade_time": "2024-08-13 10:30:00", "close": 0.681, "open": 0.681, "high": 0.682, "low": 0.68, "vol": 15768000.0, "amount": 10738531.0}, {"ts_code": "159949.SZ", "trade_time": "2024-08-13 10:15:00", "close": 0.681, "open": 0.681, "high": 0.685, "low": 0.68, "vol": 60725600.0, "amount": 41400016.0}, {"ts_code": "159949.SZ", "trade_time": "2024-08-13 10:00:00", "close": 0.682, "open": 0.683, "high": 0.685, "low": 0.681, "vol": 31828000.0, "amount": 21734624.0}, {"ts_code": "159949.SZ", "trade_time": "2024-08-13 09:45:00", "close": 0.683, "open": 0.683, "high": 0.684, "low": 0.68, "vol": 41769400.0, "amount": 28471900.0}, {"ts_code": "159949.SZ", "trade_time": "2024-08-13 09:30:00", "close": 0.682, "open": 0.682, "high": 0.683, "low": 0.681, "vol": 2203600.0, "amount": 1502955.2}], "512100.SH": [{"ts_code": "512100.SH", "trade_time": "2024-08-13 15:00:00", "close": 1.906, "open": 1.901, "high": 1.908, "low": 1.899, "vol": 65469140.0, "amount": 124733860.0}, {"ts_code": "512100.SH", "trade_time": "2024-08-13 14:45:00", "close": 1.901, "open": 1.892, "high": 1.901, "low": 1.891, "vol": 30201066.0, "amount": 57259644.0}, {"ts_code": "512100.SH", "trade_time": "2024-08-13 14:30:00", "close": 1.892, "open": 1.887, "high": 1.894, "low": 1.885, "vol": 21001800.0, "amount": 39680950.0}, {"ts_code": "512100.SH", "trade_time": "2024-08-13 14:15:00", "close": 1.888, "open": 1.894, "high": 1.894, "low": 1.886, "vol": 34252300.0, "amount": 64733084.0}, {"ts_code": "512100.SH", "trade_time": "2024-08-13 14:00:00", "close": 1.894, "open": 1.894, "high": 1.895, "low": 1.891, "vol": 10673600.0, "amount": 20207920.0}, {"ts_code": "512100.SH", "trade_time": "2024-08-13 13:45:00", "close": 1.894, "open": 1.897, "high": 1.898, "low": 1.893, "vol": 12720000.0, "amount": 24106852.0}, {"ts_code": "512100.SH", "trade_time": "2024-08-13 13:30:00", "close": 1.897, "open": 1.896, "high": 1.902, "low": 1.896, "vol": 14533400.0, "amount": 27606918.0}, {"ts_code": "512100.SH", "trade_time": "2024-08-13 13:15:00", "close": 1.897, "open": 1.896, "high": 1.898, "low": 1.893, "vol": 12136300.0, "amount": 23007724.0}, {"ts_code": "512100.SH", "trade_time": "2024-08-13 11:30:00", "close": 1.896, "open": 1.9, "high": 1.901, "low": 1.895, "vol": 7075195.0, "amount": 13425021.0}, {"ts_code": "512100.SH", "trade_time": "2024-08-13 11:15:00", "close": 1.9, "open": 1.901, "high": 1.903, "low": 1.896, "vol": 16446800.0, "amount": 31239452.0}, {"ts_code": "512100.SH", "trade_time": "2024-08-13 11:00:00", "close": 1.901, "open": 1.899, "high": 1.903, "low": 1.898, "vol": 13913300.0, "amount": 26452258.0}, {"ts_code": "512100.SH", "trade_time": "2024-08-13 10:45:00", "close": 1.899, "open": 1.902, "high": 1.902, "low": 1.896, "vol": 11319400.0, "amount": 21495024.0}, {"ts_code": "512100.SH", "trade_time": "2024-08-13 10:30:00", "close": 1.902, "open": 1.901, "high": 1.903, "low": 1.899, "vol": 21804996.0, "amount": 41454532.0}, {"ts_code": "512100.SH", "trade_time": "2024-08-13 10:15:00", "close": 1.901, "open": 1.897, "high": 1.911, "low": 1.895, "vol": 81423600.0, "amount": 154913140.0}, {"ts_code": "512100.SH", "trade_time": "2024-08-13 10:00:00", "close": 1.898, "open": 1.899, "high": 1.904, "low": 1.894, "vol": 24317724.0, "amount": 46170484.0}, {"ts_code": "512100.SH", "trade_time": "2024-08-13 09:45:00", "close": 1.899, "open": 1.899, "high": 1.905, "low": 1.89, "vol": 41130056.0, "amount": 77992900.0}, {"ts_code": "512100.SH", "trade_time": "2024-08-13 09:30:00", "close": 1.899, "open": 1.899, "high": 1.899, "low": 1.899, "vol": 1703500.0, "amount": 3234947.0}], "159845.SZ": [{"ts_code": "159845.SZ", "trade_time": "2024-08-13 15:00:00", "close": 1.912, "open": 1.906, "high": 1.913, "low": 1.904, "vol": 20924500.0, "amount": 39959188.0}, {"ts_code": "159845.SZ", "trade_time": "2024-08-13 14:45:00", "close": 1.906, "open": 1.897, "high": 1.906, "low": 1.897, "vol": 11173900.0, "amount": 21232492.0}, {"ts_code": "159845.SZ", "trade_time": "2024-08-13 14:30:00", "close": 1.897, "open": 1.891, "high": 1.898, "low": 1.89, "vol": 18629800.0, "amount": 35284980.0}, {"ts_code": "159845.SZ", "trade_time": "2024-08-13 14:15:00", "close": 1.892, "open": 1.898, "high": 1.9, "low": 1.891, "vol": 9344900.0, "amount": 17703480.0}, {"ts_code": "159845.SZ", "trade_time": "2024-08-13 14:00:00", "close": 1.898, "open": 1.898, "high": 1.9, "low": 1.897, "vol": 5647100.0, "amount": 10720412.0}, {"ts_code": "159845.SZ", "trade_time": "2024-08-13 13:45:00", "close": 1.898, "open": 1.902, "high": 1.902, "low": 1.898, "vol": 3476000.0, "amount": 6602172.5}, {"ts_code": "159845.SZ", "trade_time": "2024-08-13 13:30:00", "close": 1.902, "open": 1.901, "high": 1.906, "low": 1.901, "vol": 9237101.0, "amount": 17585844.0}, {"ts_code": "159845.SZ", "trade_time": "2024-08-13 13:15:00", "close": 1.901, "open": 1.9, "high": 1.902, "low": 1.898, "vol": 6405400.0, "amount": 12176078.0}, {"ts_code": "159845.SZ", "trade_time": "2024-08-13 11:30:00", "close": 1.901, "open": 1.903, "high": 1.905, "low": 1.9, "vol": 3490500.0, "amount": 6636793.5}, {"ts_code": "159845.SZ", "trade_time": "2024-08-13 11:15:00", "close": 1.904, "open": 1.905, "high": 1.906, "low": 1.901, "vol": 5041800.0, "amount": 9596453.0}, {"ts_code": "159845.SZ", "trade_time": "2024-08-13 11:00:00", "close": 1.905, "open": 1.904, "high": 1.908, "low": 1.903, "vol": 9225200.0, "amount": 17578474.0}, {"ts_code": "159845.SZ", "trade_time": "2024-08-13 10:45:00", "close": 1.903, "open": 1.906, "high": 1.906, "low": 1.9, "vol": 6768200.0, "amount": 12882378.0}, {"ts_code": "159845.SZ", "trade_time": "2024-08-13 10:30:00", "close": 1.906, "open": 1.905, "high": 1.908, "low": 1.903, "vol": 7281700.0, "amount": 13875103.0}, {"ts_code": "159845.SZ", "trade_time": "2024-08-13 10:15:00", "close": 1.906, "open": 1.901, "high": 1.915, "low": 1.9, "vol": 40484500.0, "amount": 77239360.0}, {"ts_code": "159845.SZ", "trade_time": "2024-08-13 10:00:00", "close": 1.901, "open": 1.903, "high": 1.907, "low": 1.898, "vol": 14695000.0, "amount": 27961880.0}, {"ts_code": "159845.SZ", "trade_time": "2024-08-13 09:45:00", "close": 1.903, "open": 1.906, "high": 1.91, "low": 1.894, "vol": 16477400.0, "amount": 31296232.0}, {"ts_code": "159845.SZ", "trade_time": "2024-08-13 09:30:00", "close": 1.905, "open": 1.905, "high": 1.905, "low": 1.902, "vol": 619300.0, "amount": 1179731.5}], "560010.SH": [{"ts_code": "560010.SH", "trade_time": "2024-08-13 15:00:00", "close": 1.906, "open": 1.901, "high": 1.908, "low": 1.9, "vol": 7967653.0, "amount": 15168654.0}, {"ts_code": "560010.SH", "trade_time": "2024-08-13 14:45:00", "close": 1.901, "open": 1.893, "high": 1.901, "low": 1.892, "vol": 8461100.0, "amount": 16047630.0}, {"ts_code": "560010.SH", "trade_time": "2024-08-13 14:30:00", "close": 1.892, "open": 1.888, "high": 1.892, "low": 1.887, "vol": 25167464.0, "amount": 47535564.0}, {"ts_code": "560010.SH", "trade_time": "2024-08-13 14:15:00", "close": 1.888, "open": 1.894, "high": 1.895, "low": 1.887, "vol": 7388700.0, "amount": 13965902.0}, {"ts_code": "560010.SH", "trade_time": "2024-08-13 14:00:00", "close": 1.895, "open": 1.895, "high": 1.896, "low": 1.893, "vol": 3524100.0, "amount": 6676184.0}, {"ts_code": "560010.SH", "trade_time": "2024-08-13 13:45:00", "close": 1.895, "open": 1.898, "high": 1.898, "low": 1.895, "vol": 3045748.0, "amount": 5775364.0}, {"ts_code": "560010.SH", "trade_time": "2024-08-13 13:30:00", "close": 1.898, "open": 1.896, "high": 1.902, "low": 1.896, "vol": 3986800.0, "amount": 7575269.0}, {"ts_code": "560010.SH", "trade_time": "2024-08-13 13:15:00", "close": 1.896, "open": 1.897, "high": 1.898, "low": 1.894, "vol": 4511200.0, "amount": 8553426.0}, {"ts_code": "560010.SH", "trade_time": "2024-08-13 11:30:00", "close": 1.896, "open": 1.899, "high": 1.9, "low": 1.895, "vol": 847700.0, "amount": 1607556.0}, {"ts_code": "560010.SH", "trade_time": "2024-08-13 11:15:00", "close": 1.9, "open": 1.9, "high": 1.901, "low": 1.896, "vol": 1507500.0, "amount": 2862524.0}, {"ts_code": "560010.SH", "trade_time": "2024-08-13 11:00:00", "close": 1.9, "open": 1.899, "high": 1.901, "low": 1.899, "vol": 628700.0, "amount": 1194650.0}, {"ts_code": "560010.SH", "trade_time": "2024-08-13 10:45:00", "close": 1.899, "open": 1.9, "high": 1.9, "low": 1.897, "vol": 2650400.0, "amount": 5032419.0}, {"ts_code": "560010.SH", "trade_time": "2024-08-13 10:30:00", "close": 1.902, "open": 1.9, "high": 1.902, "low": 1.898, "vol": 2410700.0, "amount": 4582620.0}, {"ts_code": "560010.SH", "trade_time": "2024-08-13 10:15:00", "close": 1.9, "open": 1.896, "high": 1.909, "low": 1.894, "vol": 17604700.0, "amount": 33501176.0}, {"ts_code": "560010.SH", "trade_time": "2024-08-13 10:00:00", "close": 1.896, "open": 1.897, "high": 1.902, "low": 1.892, "vol": 5928565.0, "amount": 11255128.0}, {"ts_code": "560010.SH", "trade_time": "2024-08-13 09:45:00", "close": 1.897, "open": 1.9, "high": 1.902, "low": 1.889, "vol": 7353172.0, "amount": 13940626.0}, {"ts_code": "560010.SH", "trade_time": "2024-08-13 09:30:00", "close": 1.9, "open": 1.9, "high": 1.9, "low": 1.9, "vol": 12700.0, "amount": 24130.0}], "510500.SH": [{"ts_code": "510500.SH", "trade_time": "2024-08-13 15:00:00", "close": 4.804, "open": 4.794, "high": 4.809, "low": 4.789, "vol": 31363128.0, "amount": 150501920.0}, {"ts_code": "510500.SH", "trade_time": "2024-08-13 14:45:00", "close": 4.793, "open": 4.768, "high": 4.793, "low": 4.768, "vol": 17704224.0, "amount": 84637500.0}, {"ts_code": "510500.SH", "trade_time": "2024-08-13 14:30:00", "close": 4.769, "open": 4.757, "high": 4.77, "low": 4.751, "vol": 13043199.0, "amount": 62084348.0}, {"ts_code": "510500.SH", "trade_time": "2024-08-13 14:15:00", "close": 4.758, "open": 4.774, "high": 4.776, "low": 4.757, "vol": 12508615.0, "amount": 59616320.0}, {"ts_code": "510500.SH", "trade_time": "2024-08-13 14:00:00", "close": 4.774, "open": 4.776, "high": 4.777, "low": 4.77, "vol": 9427834.0, "amount": 44998356.0}, {"ts_code": "510500.SH", "trade_time": "2024-08-13 13:45:00", "close": 4.776, "open": 4.781, "high": 4.781, "low": 4.776, "vol": 11738412.0, "amount": 56095136.0}, {"ts_code": "510500.SH", "trade_time": "2024-08-13 13:30:00", "close": 4.781, "open": 4.78, "high": 4.79, "low": 4.779, "vol": 10929762.0, "amount": 52299856.0}, {"ts_code": "510500.SH", "trade_time": "2024-08-13 13:15:00", "close": 4.78, "open": 4.776, "high": 4.783, "low": 4.774, "vol": 5747902.0, "amount": 27465778.0}, {"ts_code": "510500.SH", "trade_time": "2024-08-13 11:30:00", "close": 4.776, "open": 4.782, "high": 4.786, "low": 4.774, "vol": 5233649.0, "amount": 25009204.0}, {"ts_code": "510500.SH", "trade_time": "2024-08-13 11:15:00", "close": 4.782, "open": 4.787, "high": 4.79, "low": 4.777, "vol": 6352310.0, "amount": 30381356.0}, {"ts_code": "510500.SH", "trade_time": "2024-08-13 11:00:00", "close": 4.787, "open": 4.779, "high": 4.79, "low": 4.778, "vol": 7621000.0, "amount": 36455336.0}, {"ts_code": "510500.SH", "trade_time": "2024-08-13 10:45:00", "close": 4.779, "open": 4.787, "high": 4.787, "low": 4.776, "vol": 5594277.0, "amount": 26738508.0}, {"ts_code": "510500.SH", "trade_time": "2024-08-13 10:30:00", "close": 4.788, "open": 4.784, "high": 4.79, "low": 4.782, "vol": 7731927.0, "amount": 36997652.0}, {"ts_code": "510500.SH", "trade_time": "2024-08-13 10:15:00", "close": 4.784, "open": 4.779, "high": 4.802, "low": 4.775, "vol": 14791002.0, "amount": 70831100.0}, {"ts_code": "510500.SH", "trade_time": "2024-08-13 10:00:00", "close": 4.779, "open": 4.788, "high": 4.793, "low": 4.773, "vol": 11802142.0, "amount": 56430744.0}, {"ts_code": "510500.SH", "trade_time": "2024-08-13 09:45:00", "close": 4.787, "open": 4.795, "high": 4.802, "low": 4.769, "vol": 18203094.0, "amount": 87039660.0}, {"ts_code": "510500.SH", "trade_time": "2024-08-13 09:30:00", "close": 4.794, "open": 4.794, "high": 4.794, "low": 4.794, "vol": 296000.0, "amount": 1419024.0}], "512500.SH": [{"ts_code": "512500.SH", "trade_time": "2024-08-13 15:00:00", "close": 2.588, "open": 2.581, "high": 2.59, "low": 2.58, "vol": 4292200.0, "amount": 11099326.0}, {"ts_code": "512500.SH", "trade_time": "2024-08-13 14:45:00", "close": 2.582, "open": 2.569, "high": 2.582, "low": 2.569, "vol": 7337000.0, "amount": 18878382.0}, {"ts_code": "512500.SH", "trade_time": "2024-08-13 14:30:00", "close": 2.568, "open": 2.564, "high": 2.569, "low": 2.561, "vol": 13764700.0, "amount": 35290010.0}, {"ts_code": "512500.SH", "trade_time": "2024-08-13 14:15:00", "close": 2.563, "open": 2.571, "high": 2.572, "low": 2.563, "vol": 9833900.0, "amount": 25259564.0}, {"ts_code": "512500.SH", "trade_time": "2024-08-13 14:00:00", "close": 2.572, "open": 2.572, "high": 2.573, "low": 2.569, "vol": 7096700.0, "amount": 18246532.0}, {"ts_code": "512500.SH", "trade_time": "2024-08-13 13:45:00", "close": 2.573, "open": 2.574, "high": 2.576, "low": 2.572, "vol": 7400100.0, "amount": 19046796.0}, {"ts_code": "512500.SH", "trade_time": "2024-08-13 13:30:00", "close": 2.575, "open": 2.572, "high": 2.58, "low": 2.572, "vol": 10744800.0, "amount": 27684026.0}, {"ts_code": "512500.SH", "trade_time": "2024-08-13 13:15:00", "close": 2.572, "open": 2.571, "high": 2.576, "low": 2.57, "vol": 6838356.0, "amount": 17595854.0}, {"ts_code": "512500.SH", "trade_time": "2024-08-13 11:30:00", "close": 2.571, "open": 2.575, "high": 2.578, "low": 2.571, "vol": 6668100.0, "amount": 17159170.0}, {"ts_code": "512500.SH", "trade_time": "2024-08-13 11:15:00", "close": 2.577, "open": 2.578, "high": 2.58, "low": 2.575, "vol": 1733900.0, "amount": 4468754.0}, {"ts_code": "512500.SH", "trade_time": "2024-08-13 11:00:00", "close": 2.579, "open": 2.574, "high": 2.58, "low": 2.574, "vol": 2090100.0, "amount": 5387470.0}, {"ts_code": "512500.SH", "trade_time": "2024-08-13 10:45:00", "close": 2.575, "open": 2.579, "high": 2.579, "low": 2.573, "vol": 2022100.0, "amount": 5205897.0}, {"ts_code": "512500.SH", "trade_time": "2024-08-13 10:30:00", "close": 2.579, "open": 2.576, "high": 2.58, "low": 2.575, "vol": 876700.0, "amount": 2259021.0}, {"ts_code": "512500.SH", "trade_time": "2024-08-13 10:15:00", "close": 2.575, "open": 2.576, "high": 2.586, "low": 2.573, "vol": 4610200.0, "amount": 11892968.0}, {"ts_code": "512500.SH", "trade_time": "2024-08-13 10:00:00", "close": 2.577, "open": 2.582, "high": 2.583, "low": 2.573, "vol": 1431400.0, "amount": 3689620.0}, {"ts_code": "512500.SH", "trade_time": "2024-08-13 09:45:00", "close": 2.579, "open": 2.584, "high": 2.586, "low": 2.569, "vol": 9894600.0, "amount": 25505844.0}, {"ts_code": "512500.SH", "trade_time": "2024-08-13 09:30:00", "close": 2.584, "open": 2.584, "high": 2.584, "low": 2.584, "vol": 2000.0, "amount": 5168.0}]}