[{"ts_code": "A.DCE", "trade_date": "20250911", "open": 3905.0, "high": 3947.0, "low": 3905.0, "close": 3945.0, "pre_close": 3911.0, "vol": 103597.0, "amount": 406769.9, "oi": 209619.0, "symbol": "A", "sector": "农产品"}, {"ts_code": "AG.SHF", "trade_date": "20250911", "open": 9803.0, "high": 9848.0, "low": 9748.0, "close": 9798.0, "pre_close": 9796.0, "vol": 301985.0, "amount": 4441136.75, "oi": 203343.0, "symbol": "AG", "sector": "贵金属"}, {"ts_code": "AL.DCE", "trade_date": "20250911", "open": null, "high": null, "low": null, "close": 4040.0, "pre_close": 4040.0, "vol": 0.0, "amount": 0.0, "oi": 63.0, "symbol": "AL", "sector": "有色金属"}, {"ts_code": "AL.SHF", "trade_date": "20250911", "open": 20780.0, "high": 20920.0, "low": 20750.0, "close": 20915.0, "pre_close": 20790.0, "vol": 106885.0, "amount": 1114492.5, "oi": 204582.0, "symbol": "AL", "sector": "有色金属"}, {"ts_code": "AO.SHF", "trade_date": "20250911", "open": 2923.0, "high": 2962.0, "low": 2923.0, "close": 2945.0, "pre_close": 2933.0, "vol": 249216.0, "amount": 1465488.79, "oi": 273311.0, "symbol": "AO", "sector": "有色金属"}, {"ts_code": "AP.ZCE", "trade_date": "20250911", "open": 8159.0, "high": 8271.0, "low": 8131.0, "close": 8252.0, "pre_close": 8130.0, "vol": 82334.0, "amount": 676253.31, "oi": 85099.0, "symbol": "AP", "sector": "农产品"}, {"ts_code": "AU.SHF", "trade_date": "20250911", "open": 833.38, "high": 836.62, "low": 828.5, "close": 830.78, "pre_close": 833.42, "vol": 165360.0, "amount": 13780848.94, "oi": 114423.0, "symbol": "AU", "sector": "贵金属"}, {"ts_code": "B.DCE", "trade_date": "20250911", "open": 3700.0, "high": 3755.0, "low": 3697.0, "close": 3755.0, "pre_close": 3698.0, "vol": 122398.0, "amount": 456061.26, "oi": 120399.0, "symbol": "B", "sector": "农产品"}, {"ts_code": "BC.INE", "trade_date": "20250911", "open": 70980.0, "high": 71360.0, "low": 70980.0, "close": 71240.0, "pre_close": 70910.0, "vol": 3550.0, "amount": 126352.4, "oi": 4378.0, "symbol": "BC", "sector": "有色金属"}, {"ts_code": "BR.SHF", "trade_date": "20250911", "open": 11720.0, "high": 11770.0, "low": 11550.0, "close": 11655.0, "pre_close": 11720.0, "vol": 62200.0, "amount": 362836.36, "oi": 22243.0, "symbol": "BR", "sector": "能源化工"}, {"ts_code": "BU.SHF", "trade_date": "20250911", "open": 3448.0, "high": 3484.0, "low": 3439.0, "close": 3463.0, "pre_close": 3450.0, "vol": 186437.0, "amount": 644981.55, "oi": 252780.0, "symbol": "BU", "sector": "能源化工"}, {"ts_code": "C.DCE", "trade_date": "20250911", "open": 2199.0, "high": 2205.0, "low": 2194.0, "close": 2202.0, "pre_close": 2197.0, "vol": 358208.0, "amount": 787942.19, "oi": 852554.0, "symbol": "C", "sector": "农产品"}, {"ts_code": "CF.ZCE", "trade_date": "20250911", "open": 13865.0, "high": 13890.0, "low": 13785.0, "close": 13835.0, "pre_close": 13855.0, "vol": 161137.0, "amount": 1114391.69, "oi": 502476.0, "symbol": "CF", "sector": "农产品"}, {"ts_code": "CJ.ZCE", "trade_date": "20250911", "open": 11045.0, "high": 11285.0, "low": 10965.0, "close": 11225.0, "pre_close": 11035.0, "vol": 165107.0, "amount": 923262.81, "oi": 137660.0, "symbol": "CJ", "sector": "农产品"}, {"ts_code": "CS.DCE", "trade_date": "20250911", "open": 2489.0, "high": 2492.0, "low": 2475.0, "close": 2477.0, "pre_close": 2488.0, "vol": 114975.0, "amount": 285269.1, "oi": 210207.0, "symbol": "CS", "sector": "农产品"}, {"ts_code": "CU.SHF", "trade_date": "20250911", "open": 79950.0, "high": 80280.0, "low": 79870.0, "close": 80130.0, "pre_close": 79790.0, "vol": 64849.0, "amount": 2596852.06, "oi": 174453.0, "symbol": "CU", "sector": "有色金属"}, {"ts_code": "CY.ZCE", "trade_date": "20250911", "open": 19875.0, "high": 19960.0, "low": 19825.0, "close": 19870.0, "pre_close": 19895.0, "vol": 9781.0, "amount": 97202.48, "oi": 22143.0, "symbol": "CY", "sector": "农产品"}, {"ts_code": "EB.DCE", "trade_date": "20250911", "open": 7070.0, "high": 7104.0, "low": 7061.0, "close": 7081.0, "pre_close": 7065.0, "vol": 166888.0, "amount": 591054.33, "oi": 272099.0, "symbol": "EB", "sector": "能源化工"}, {"ts_code": "EG.DCE", "trade_date": "20250911", "open": 4320.0, "high": 4324.0, "low": 4291.0, "close": 4302.0, "pre_close": 4319.0, "vol": 134693.0, "amount": 580119.07, "oi": 309072.0, "symbol": "EG", "sector": "能源化工"}, {"ts_code": "FG.ZCE", "trade_date": "20250911", "open": 1182.0, "high": 1202.0, "low": 1175.0, "close": 1185.0, "pre_close": 1181.0, "vol": 1662007.0, "amount": 3942012.78, "oi": 1296988.0, "symbol": "FG", "sector": "能源化工"}, {"ts_code": "FU.SHF", "trade_date": "20250911", "open": 2781.0, "high": 2810.0, "low": 2774.0, "close": 2802.0, "pre_close": 2786.0, "vol": 375743.0, "amount": 1049556.84, "oi": 202394.0, "symbol": "FU", "sector": "能源化工"}, {"ts_code": "HC.SHF", "trade_date": "20250911", "open": 3347.0, "high": 3354.0, "low": 3330.0, "close": 3334.0, "pre_close": 3342.0, "vol": 485423.0, "amount": 1622620.18, "oi": 1323310.0, "symbol": "HC", "sector": "黑色系"}, {"ts_code": "I.DCE", "trade_date": "20250911", "open": 804.5, "high": 809.0, "low": 791.5, "close": 795.5, "pre_close": 805.0, "vol": 365052.0, "amount": 2921100.79, "oi": 538976.0, "symbol": "I", "sector": "黑色系"}, {"ts_code": "J.DCE", "trade_date": "20250911", "open": 1605.0, "high": 1635.5, "low": 1601.0, "close": 1630.0, "pre_close": 1603.0, "vol": 22593.0, "amount": 365690.34, "oi": 46939.0, "symbol": "J", "sector": "黑色系"}, {"ts_code": "JD.DCE", "trade_date": "20250911", "open": 3021.0, "high": 3063.0, "low": 3014.0, "close": 3044.0, "pre_close": 3019.0, "vol": 446708.0, "amount": 1357752.99, "oi": 406138.0, "symbol": "JD", "sector": "农产品"}, {"ts_code": "JM.DCE", "trade_date": "20250911", "open": 1117.5, "high": 1149.0, "low": 1117.5, "close": 1141.5, "pre_close": 1117.0, "vol": 1064365.0, "amount": 7247263.48, "oi": 718075.0, "symbol": "JM", "sector": "黑色系"}, {"ts_code": "L.DCE", "trade_date": "20250911", "open": 7222.0, "high": 7240.0, "low": 7196.0, "close": 7209.0, "pre_close": 7226.0, "vol": 217976.0, "amount": 786484.72, "oi": 533469.0, "symbol": "L", "sector": "能源化工"}, {"ts_code": "LH.DCE", "trade_date": "20250911", "open": 13350.0, "high": 13370.0, "low": 13285.0, "close": 13320.0, "pre_close": 13315.0, "vol": 21207.0, "amount": 451927.58, "oi": 75953.0, "symbol": "LH", "sector": "农产品"}, {"ts_code": "LU.INE", "trade_date": "20250911", "open": 3379.0, "high": 3390.0, "low": 3351.0, "close": 3374.0, "pre_close": 3383.0, "vol": 82588.0, "amount": 278388.67, "oi": 75318.0, "symbol": "LU", "sector": "能源化工"}, {"ts_code": "M.DCE", "trade_date": "20250911", "open": 3067.0, "high": 3090.0, "low": 3064.0, "close": 3088.0, "pre_close": 3066.0, "vol": 798021.0, "amount": 2454543.8, "oi": 2001532.0, "symbol": "M", "sector": "农产品"}, {"ts_code": "MA.ZCE", "trade_date": "20250911", "open": 2404.0, "high": 2409.0, "low": 2381.0, "close": 2387.0, "pre_close": 2407.0, "vol": 493157.0, "amount": 1180908.94, "oi": 775400.0, "symbol": "MA", "sector": "能源化工"}, {"ts_code": "NI.SHF", "trade_date": "20250911", "open": 120520.0, "high": 120910.0, "low": 120110.0, "close": 120620.0, "pre_close": 120850.0, "vol": 87538.0, "amount": 1054424.41, "oi": 81691.0, "symbol": "NI", "sector": "有色金属"}, {"ts_code": "NR.INE", "trade_date": "20250911", "open": 12770.0, "high": 12770.0, "low": 12485.0, "close": 12620.0, "pre_close": 12715.0, "vol": 90869.0, "amount": 1145171.83, "oi": 73296.0, "symbol": "NR", "sector": "能源化工"}, {"ts_code": "OI.ZCE", "trade_date": "20250911", "open": 9782.0, "high": 9897.0, "low": 9774.0, "close": 9893.0, "pre_close": 9770.0, "vol": 300917.0, "amount": 2960863.58, "oi": 286194.0, "symbol": "OI", "sector": "农产品"}, {"ts_code": "P.DCE", "trade_date": "20250911", "open": 9280.0, "high": 9334.0, "low": 9208.0, "close": 9330.0, "pre_close": 9244.0, "vol": 719314.0, "amount": 6671551.58, "oi": 438697.0, "symbol": "P", "sector": "农产品"}, {"ts_code": "PB.SHF", "trade_date": "20250911", "open": 16815.0, "high": 16920.0, "low": 16790.0, "close": 16900.0, "pre_close": 16795.0, "vol": 41772.0, "amount": 352145.47, "oi": 49603.0, "symbol": "PB", "sector": "有色金属"}, {"ts_code": "PF.ZCE", "trade_date": "20250911", "open": 6370.0, "high": 6390.0, "low": 6340.0, "close": 6370.0, "pre_close": 6364.0, "vol": 113791.0, "amount": 362115.37, "oi": 182894.0, "symbol": "PF", "sector": "能源化工"}, {"ts_code": "PG.DCE", "trade_date": "20250911", "open": 4462.0, "high": 4475.0, "low": 4437.0, "close": 4470.0, "pre_close": 4462.0, "vol": 58811.0, "amount": 523803.9, "oi": 67360.0, "symbol": "PG", "sector": "能源化工"}, {"ts_code": "PK.ZCE", "trade_date": "20250911", "open": 7794.0, "high": 7798.0, "low": 7752.0, "close": 7786.0, "pre_close": 7794.0, "vol": 93142.0, "amount": 362088.71, "oi": 132623.0, "symbol": "PK", "sector": "农产品"}, {"ts_code": "PP.DCE", "trade_date": "20250911", "open": 6952.0, "high": 6964.0, "low": 6927.0, "close": 6939.0, "pre_close": 6948.0, "vol": 197721.0, "amount": 686470.14, "oi": 624199.0, "symbol": "PP", "sector": "能源化工"}, {"ts_code": "PX.ZCE", "trade_date": "20250911", "open": 6760.0, "high": 6808.0, "low": 6740.0, "close": 6778.0, "pre_close": 6770.0, "vol": 118939.0, "amount": 402333.89, "oi": 153943.0, "symbol": "PX", "sector": "能源化工"}, {"ts_code": "RB.SHF", "trade_date": "20250911", "open": 3110.0, "high": 3119.0, "low": 3082.0, "close": 3092.0, "pre_close": 3109.0, "vol": 1542810.0, "amount": 4784746.92, "oi": 2000701.0, "symbol": "RB", "sector": "黑色系"}, {"ts_code": "RI.ZCE", "trade_date": "20250911", "open": null, "high": null, "low": null, "close": 2479.0, "pre_close": 2479.0, "vol": 0.0, "amount": 0.0, "oi": 0.0, "symbol": "RI", "sector": "农产品"}, {"ts_code": "RM.ZCE", "trade_date": "20250911", "open": 2538.0, "high": 2568.0, "low": 2535.0, "close": 2567.0, "pre_close": 2533.0, "vol": 341171.0, "amount": 871292.35, "oi": 407316.0, "symbol": "RM", "sector": "农产品"}, {"ts_code": "RR.DCE", "trade_date": "20250911", "open": 3608.0, "high": 3612.0, "low": 3596.0, "close": 3598.0, "pre_close": 3610.0, "vol": 1546.0, "amount": 5571.39, "oi": 6883.0, "symbol": "RR", "sector": "农产品"}, {"ts_code": "RU.SHF", "trade_date": "20250911", "open": 15980.0, "high": 16010.0, "low": 15790.0, "close": 15905.0, "pre_close": 15980.0, "vol": 281078.0, "amount": 4464767.57, "oi": 150967.0, "symbol": "RU", "sector": "能源化工"}, {"ts_code": "SA.ZCE", "trade_date": "20250911", "open": 1281.0, "high": 1297.0, "low": 1275.0, "close": 1287.0, "pre_close": 1281.0, "vol": 1102427.0, "amount": 2835127.0, "oi": 1440308.0, "symbol": "SA", "sector": "能源化工"}, {"ts_code": "SC.INE", "trade_date": "20250911", "open": 485.1, "high": 492.8, "low": 485.1, "close": 489.2, "pre_close": 486.2, "vol": 88080.0, "amount": 4305277.99, "oi": 21916.0, "symbol": "SC", "sector": "能源化工"}, {"ts_code": "SF.ZCE", "trade_date": "20250911", "open": 5640.0, "high": 5674.0, "low": 5610.0, "close": 5626.0, "pre_close": 5628.0, "vol": 125843.0, "amount": 354891.96, "oi": 213441.0, "symbol": "SF", "sector": "黑色系"}, {"ts_code": "SI.GFE", "trade_date": "20250911", "open": 8715.0, "high": 8780.0, "low": 8630.0, "close": 8740.0, "pre_close": 8665.0, "vol": 347619.0, "amount": 1510599.57, "oi": 287771.0, "symbol": "SI", "sector": "有色金属"}, {"ts_code": "SM.ZCE", "trade_date": "20250911", "open": 5862.0, "high": 5890.0, "low": 5832.0, "close": 5838.0, "pre_close": 5854.0, "vol": 148763.0, "amount": 435829.94, "oi": 324305.0, "symbol": "SM", "sector": "黑色系"}, {"ts_code": "SN.SHF", "trade_date": "20250911", "open": 271180.0, "high": 272680.0, "low": 270430.0, "close": 271260.0, "pre_close": 270430.0, "vol": 57815.0, "amount": 1569202.92, "oi": 26606.0, "symbol": "SN", "sector": "有色金属"}, {"ts_code": "SP.SHF", "trade_date": "20250911", "open": 4996.0, "high": 5022.0, "low": 4966.0, "close": 5016.0, "pre_close": 4996.0, "vol": 253461.0, "amount": 1265952.66, "oi": 190457.0, "symbol": "SP", "sector": "能源化工"}, {"ts_code": "SR.ZCE", "trade_date": "20250911", "open": 5545.0, "high": 5558.0, "low": 5527.0, "close": 5556.0, "pre_close": 5535.0, "vol": 155411.0, "amount": 861291.03, "oi": 391605.0, "symbol": "SR", "sector": "农产品"}, {"ts_code": "SS.SHF", "trade_date": "20250911", "open": 12905.0, "high": 12930.0, "low": 12860.0, "close": 12870.0, "pre_close": 12915.0, "vol": 112848.0, "amount": 727657.94, "oi": 128344.0, "symbol": "SS", "sector": "黑色系"}, {"ts_code": "TA.ZCE", "trade_date": "20250911", "open": 4690.0, "high": 4712.0, "low": 4670.0, "close": 4688.0, "pre_close": 4698.0, "vol": 441976.0, "amount": 1036039.18, "oi": 1000445.0, "symbol": "TA", "sector": "能源化工"}, {"ts_code": "UR.ZCE", "trade_date": "20250911", "open": 1669.0, "high": 1676.0, "low": 1666.0, "close": 1671.0, "pre_close": 1669.0, "vol": 125326.0, "amount": 419032.87, "oi": 292643.0, "symbol": "UR", "sector": "能源化工"}, {"ts_code": "V.DCE", "trade_date": "20250911", "open": 4852.0, "high": 4896.0, "low": 4838.0, "close": 4888.0, "pre_close": 4857.0, "vol": 729601.0, "amount": 1774487.1, "oi": 1242667.0, "symbol": "V", "sector": "能源化工"}, {"ts_code": "WH.ZCE", "trade_date": "20250911", "open": null, "high": null, "low": null, "close": 3198.0, "pre_close": 3198.0, "vol": 0.0, "amount": 0.0, "oi": 0.0, "symbol": "WH", "sector": "农产品"}, {"ts_code": "Y.DCE", "trade_date": "20250911", "open": 8272.0, "high": 8342.0, "low": 8262.0, "close": 8336.0, "pre_close": 8256.0, "vol": 304700.0, "amount": 2526746.98, "oi": 599383.0, "symbol": "Y", "sector": "农产品"}, {"ts_code": "ZN.SHF", "trade_date": "20250911", "open": 22205.0, "high": 22285.0, "low": 22145.0, "close": 22250.0, "pre_close": 22215.0, "vol": 93321.0, "amount": 1037208.67, "oi": 100442.0, "symbol": "ZN", "sector": "有色金属"}]